[
    {
        "price_close": 7295.19,
        "price_high": 7295.19,
        "price_low": 7291.94,
        "price_open": 7291.94,
        "time_close": "2018-09-03T00:00:46.0000000Z",
        "time_open": "2018-09-03T00:00:19.0000000Z",
        "time_period_end": "2018-09-03T00:01:00.0000000Z",
        "time_period_start": "2018-09-03T00:00:00.0000000Z",
        "trades_count": 7,
        "volume_traded": 0.52016231
    },
    {
        "price_close": 7298.06,
        "price_high": 7307.39,
        "price_low": 7297.01,
        "price_open": 7297.01,
        "time_close": "2018-09-03T00:01:58.0000000Z",
        "time_open": "2018-09-03T00:01:05.0000000Z",
        "time_period_end": "2018-09-03T00:02:00.0000000Z",
        "time_period_start": "2018-09-03T00:01:00.0000000Z",
        "trades_count": 25,
        "volume_traded": 2.96163528
    },
    {
        "price_close": 7295.13,
        "price_high": 7301.26,
        "price_low": 7289.29,
        "price_open": 7301.26,
        "time_close": "2018-09-03T00:02:39.0000000Z",
        "time_open": "2018-09-03T00:02:00.0000000Z",
        "time_period_end": "2018-09-03T00:03:00.0000000Z",
        "time_period_start": "2018-09-03T00:02:00.0000000Z",
        "trades_count": 4,
        "volume_traded": 0.3164731
    },
    {
        "price_close": 7290.13,
        "price_high": 7292.68,
        "price_low": 7290.13,
        "price_open": 7292.68,
        "time_close": "2018-09-03T00:03:54.0000000Z",
        "time_open": "2018-09-03T00:03:41.0000000Z",
        "time_period_end": "2018-09-03T00:04:00.0000000Z",
        "time_period_start": "2018-09-03T00:03:00.0000000Z",
        "trades_count": 5,
        "volume_traded": 0.03815802
    },
    {
        "price_close": 7299.99,
        "price_high": 7299.99,
        "price_low": 7294.99,
        "price_open": 7294.99,
        "time_close": "2018-09-03T00:04:41.0000000Z",
        "time_open": "2018-09-03T00:04:19.0000000Z",
        "time_period_end": "2018-09-03T00:05:00.0000000Z",
        "time_period_start": "2018-09-03T00:04:00.0000000Z",
        "trades_count": 16,
        "volume_traded": 0.02511487
    },
    {
        "price_close": 7301.07,
        "price_high": 7308.54,
        "price_low": 7300.05,
        "price_open": 7300.05,
        "time_close": "2018-09-03T00:05:57.0000000Z",
        "time_open": "2018-09-03T00:05:49.0000000Z",
        "time_period_end": "2018-09-03T00:06:00.0000000Z",
        "time_period_start": "2018-09-03T00:05:00.0000000Z",
        "trades_count": 15,
        "volume_traded": 0.18448033
    },
    {
        "price_close": 7301.46,
        "price_high": 7304.42,
        "price_low": 7301.06,
        "price_open": 7301.06,
        "time_close": "2018-09-03T00:06:46.0000000Z",
        "time_open": "2018-09-03T00:06:19.0000000Z",
        "time_period_end": "2018-09-03T00:07:00.0000000Z",
        "time_period_start": "2018-09-03T00:06:00.0000000Z",
        "trades_count": 14,
        "volume_traded": 2.39220052
    },
    {
        "price_close": 7298.28,
        "price_high": 7298.28,
        "price_low": 7298.28,
        "price_open": 7298.28,
        "time_close": "2018-09-03T00:07:19.0000000Z",
        "time_open": "2018-09-03T00:07:19.0000000Z",
        "time_period_end": "2018-09-03T00:08:00.0000000Z",
        "time_period_start": "2018-09-03T00:07:00.0000000Z",
        "trades_count": 1,
        "volume_traded": 0.00101202
    },
    {
        "price_close": 7300.46,
        "price_high": 7307.3,
        "price_low": 7300.46,
        "price_open": 7303.88,
        "time_close": "2018-09-03T00:08:45.0000000Z",
        "time_open": "2018-09-03T00:08:10.0000000Z",
        "time_period_end": "2018-09-03T00:09:00.0000000Z",
        "time_period_start": "2018-09-03T00:08:00.0000000Z",
        "trades_count": 16,
        "volume_traded": 0.57542286
    },
    {
        "price_close": 7308.67,
        "price_high": 7308.67,
        "price_low": 7307.29,
        "price_open": 7307.29,
        "time_close": "2018-09-03T00:09:46.0000000Z",
        "time_open": "2018-09-03T00:09:13.0000000Z",
        "time_period_end": "2018-09-03T00:10:00.0000000Z",
        "time_period_start": "2018-09-03T00:09:00.0000000Z",
        "trades_count": 12,
        "volume_traded": 0.88356459
    },
    {
        "price_close": 7318.98,
        "price_high": 7319.11,
        "price_low": 7308.7,
        "price_open": 7308.7,
        "time_close": "2018-09-03T00:10:31.0000000Z",
        "time_open": "2018-09-03T00:10:08.0000000Z",
        "time_period_end": "2018-09-03T00:11:00.0000000Z",
        "time_period_start": "2018-09-03T00:10:00.0000000Z",
        "trades_count": 21,
        "volume_traded": 0.71025635
    },
    {
        "price_close": 7309.99,
        "price_high": 7309.99,
        "price_low": 7306.18,
        "price_open": 7308.72,
        "time_close": "2018-09-03T00:11:39.0000000Z",
        "time_open": "2018-09-03T00:11:03.0000000Z",
        "time_period_end": "2018-09-03T00:12:00.0000000Z",
        "time_period_start": "2018-09-03T00:11:00.0000000Z",
        "trades_count": 7,
        "volume_traded": 0.57215603
    },
    {
        "price_close": 7316.09,
        "price_high": 7316.17,
        "price_low": 7310.68,
        "price_open": 7313.06,
        "time_close": "2018-09-03T00:12:47.0000000Z",
        "time_open": "2018-09-03T00:12:06.0000000Z",
        "time_period_end": "2018-09-03T00:13:00.0000000Z",
        "time_period_start": "2018-09-03T00:12:00.0000000Z",
        "trades_count": 18,
        "volume_traded": 0.93834143
    },
    {
        "price_close": 7311.76,
        "price_high": 7311.76,
        "price_low": 7306.18,
        "price_open": 7307.36,
        "time_close": "2018-09-03T00:13:52.0000000Z",
        "time_open": "2018-09-03T00:13:19.0000000Z",
        "time_period_end": "2018-09-03T00:14:00.0000000Z",
        "time_period_start": "2018-09-03T00:13:00.0000000Z",
        "trades_count": 3,
        "volume_traded": 0.03586489
    },
    {
        "price_close": 7303.87,
        "price_high": 7308.71,
        "price_low": 7303.87,
        "price_open": 7307.5,
        "time_close": "2018-09-03T00:14:57.0000000Z",
        "time_open": "2018-09-03T00:14:10.0000000Z",
        "time_period_end": "2018-09-03T00:15:00.0000000Z",
        "time_period_start": "2018-09-03T00:14:00.0000000Z",
        "trades_count": 9,
        "volume_traded": 0.26728344
    },
    {
        "price_close": 7304.99,
        "price_high": 7304.99,
        "price_low": 7302.0,
        "price_open": 7302.99,
        "time_close": "2018-09-03T00:15:36.0000000Z",
        "time_open": "2018-09-03T00:15:30.0000000Z",
        "time_period_end": "2018-09-03T00:16:00.0000000Z",
        "time_period_start": "2018-09-03T00:15:00.0000000Z",
        "trades_count": 13,
        "volume_traded": 0.05282329
    },
    {
        "price_close": 7295.99,
        "price_high": 7301.81,
        "price_low": 7288.14,
        "price_open": 7301.52,
        "time_close": "2018-09-03T00:16:55.0000000Z",
        "time_open": "2018-09-03T00:16:02.0000000Z",
        "time_period_end": "2018-09-03T00:17:00.0000000Z",
        "time_period_start": "2018-09-03T00:16:00.0000000Z",
        "trades_count": 17,
        "volume_traded": 4.5673767
    },
    {
        "price_close": 7295.99,
        "price_high": 7295.99,
        "price_low": 7295.9,
        "price_open": 7295.9,
        "time_close": "2018-09-03T00:17:58.0000000Z",
        "time_open": "2018-09-03T00:17:30.0000000Z",
        "time_period_end": "2018-09-03T00:18:00.0000000Z",
        "time_period_start": "2018-09-03T00:17:00.0000000Z",
        "trades_count": 21,
        "volume_traded": 0.22847351
    },
    {
        "price_close": 7292.94,
        "price_high": 7292.94,
        "price_low": 7292.94,
        "price_open": 7292.94,
        "time_close": "2018-09-03T00:18:25.0000000Z",
        "time_open": "2018-09-03T00:18:11.0000000Z",
        "time_period_end": "2018-09-03T00:19:00.0000000Z",
        "time_period_start": "2018-09-03T00:18:00.0000000Z",
        "trades_count": 4,
        "volume_traded": 0.25138433
    },
    {
        "price_close": 7292.94,
        "price_high": 7292.94,
        "price_low": 7292.94,
        "price_open": 7292.94,
        "time_close": "2018-09-03T00:19:57.0000000Z",
        "time_open": "2018-09-03T00:19:18.0000000Z",
        "time_period_end": "2018-09-03T00:20:00.0000000Z",
        "time_period_start": "2018-09-03T00:19:00.0000000Z",
        "trades_count": 8,
        "volume_traded": 0.12542714
    },
    {
        "price_close": 7284.41,
        "price_high": 7292.93,
        "price_low": 7284.4,
        "price_open": 7292.93,
        "time_close": "2018-09-03T00:20:40.0000000Z",
        "time_open": "2018-09-03T00:20:07.0000000Z",
        "time_period_end": "2018-09-03T00:21:00.0000000Z",
        "time_period_start": "2018-09-03T00:20:00.0000000Z",
        "trades_count": 5,
        "volume_traded": 1.40713549
    },
    {
        "price_close": 7286.76,
        "price_high": 7286.76,
        "price_low": 7286.75,
        "price_open": 7286.75,
        "time_close": "2018-09-03T00:21:26.0000000Z",
        "time_open": "2018-09-03T00:21:19.0000000Z",
        "time_period_end": "2018-09-03T00:22:00.0000000Z",
        "time_period_start": "2018-09-03T00:21:00.0000000Z",
        "trades_count": 2,
        "volume_traded": 0.03574037
    },
    {
        "price_close": 7297.17,
        "price_high": 7297.17,
        "price_low": 7286.76,
        "price_open": 7286.76,
        "time_close": "2018-09-03T00:22:20.0000000Z",
        "time_open": "2018-09-03T00:22:17.0000000Z",
        "time_period_end": "2018-09-03T00:23:00.0000000Z",
        "time_period_start": "2018-09-03T00:22:00.0000000Z",
        "trades_count": 12,
        "volume_traded": 0.39009218
    },
    {
        "price_close": 7291.7,
        "price_high": 7295.81,
        "price_low": 7291.7,
        "price_open": 7293.99,
        "time_close": "2018-09-03T00:23:48.0000000Z",
        "time_open": "2018-09-03T00:23:25.0000000Z",
        "time_period_end": "2018-09-03T00:24:00.0000000Z",
        "time_period_start": "2018-09-03T00:23:00.0000000Z",
        "trades_count": 7,
        "volume_traded": 0.28425844
    },
    {
        "price_close": 7290.06,
        "price_high": 7290.06,
        "price_low": 7290.06,
        "price_open": 7290.06,
        "time_close": "2018-09-03T00:24:35.0000000Z",
        "time_open": "2018-09-03T00:24:35.0000000Z",
        "time_period_end": "2018-09-03T00:25:00.0000000Z",
        "time_period_start": "2018-09-03T00:24:00.0000000Z",
        "trades_count": 1,
        "volume_traded": 0.2
    },
    {
        "price_close": 7286.85,
        "price_high": 7286.85,
        "price_low": 7286.84,
        "price_open": 7286.84,
        "time_close": "2018-09-03T00:25:55.0000000Z",
        "time_open": "2018-09-03T00:25:53.0000000Z",
        "time_period_end": "2018-09-03T00:26:00.0000000Z",
        "time_period_start": "2018-09-03T00:25:00.0000000Z",
        "trades_count": 2,
        "volume_traded": 0.07802555
    },
    {
        "price_close": 7286.99,
        "price_high": 7286.99,
        "price_low": 7286.85,
        "price_open": 7286.85,
        "time_close": "2018-09-03T00:26:22.0000000Z",
        "time_open": "2018-09-03T00:26:21.0000000Z",
        "time_period_end": "2018-09-03T00:27:00.0000000Z",
        "time_period_start": "2018-09-03T00:26:00.0000000Z",
        "trades_count": 7,
        "volume_traded": 0.16447941
    },
    {
        "price_close": 7290.99,
        "price_high": 7290.99,
        "price_low": 7289.99,
        "price_open": 7290.22,
        "time_close": "2018-09-03T00:28:38.0000000Z",
        "time_open": "2018-09-03T00:28:04.0000000Z",
        "time_period_end": "2018-09-03T00:29:00.0000000Z",
        "time_period_start": "2018-09-03T00:28:00.0000000Z",
        "trades_count": 6,
        "volume_traded": 0.58921814
    },
    {
        "price_close": 7289.99,
        "price_high": 7289.99,
        "price_low": 7282.77,
        "price_open": 7282.77,
        "time_close": "2018-09-03T00:30:34.0000000Z",
        "time_open": "2018-09-03T00:30:08.0000000Z",
        "time_period_end": "2018-09-03T00:31:00.0000000Z",
        "time_period_start": "2018-09-03T00:30:00.0000000Z",
        "trades_count": 4,
        "volume_traded": 0.05740261
    },
    {
        "price_close": 7290.64,
        "price_high": 7290.64,
        "price_low": 7287.99,
        "price_open": 7287.99,
        "time_close": "2018-09-03T00:32:57.0000000Z",
        "time_open": "2018-09-03T00:32:43.0000000Z",
        "time_period_end": "2018-09-03T00:33:00.0000000Z",
        "time_period_start": "2018-09-03T00:32:00.0000000Z",
        "trades_count": 6,
        "volume_traded": 1.59458204
    },
    {
        "price_close": 7273.25,
        "price_high": 7288.08,
        "price_low": 7266.01,
        "price_open": 7287.99,
        "time_close": "2018-09-03T00:33:52.0000000Z",
        "time_open": "2018-09-03T00:33:01.0000000Z",
        "time_period_end": "2018-09-03T00:34:00.0000000Z",
        "time_period_start": "2018-09-03T00:33:00.0000000Z",
        "trades_count": 20,
        "volume_traded": 6.74097433
    },
    {
        "price_close": 7278.76,
        "price_high": 7281.99,
        "price_low": 7272.41,
        "price_open": 7273.24,
        "time_close": "2018-09-03T00:34:57.0000000Z",
        "time_open": "2018-09-03T00:34:02.0000000Z",
        "time_period_end": "2018-09-03T00:35:00.0000000Z",
        "time_period_start": "2018-09-03T00:34:00.0000000Z",
        "trades_count": 10,
        "volume_traded": 1.78303845
    },
    {
        "price_close": 7273.28,
        "price_high": 7279.99,
        "price_low": 7270.11,
        "price_open": 7270.21,
        "time_close": "2018-09-03T00:35:41.0000000Z",
        "time_open": "2018-09-03T00:35:01.0000000Z",
        "time_period_end": "2018-09-03T00:36:00.0000000Z",
        "time_period_start": "2018-09-03T00:35:00.0000000Z",
        "trades_count": 18,
        "volume_traded": 8.56285844
    },
    {
        "price_close": 7278.01,
        "price_high": 7278.07,
        "price_low": 7278.01,
        "price_open": 7278.06,
        "time_close": "2018-09-03T00:36:19.0000000Z",
        "time_open": "2018-09-03T00:36:01.0000000Z",
        "time_period_end": "2018-09-03T00:37:00.0000000Z",
        "time_period_start": "2018-09-03T00:36:00.0000000Z",
        "trades_count": 3,
        "volume_traded": 1.04094334
    },
    {
        "price_close": 7281.73,
        "price_high": 7282.89,
        "price_low": 7278.01,
        "price_open": 7278.01,
        "time_close": "2018-09-03T00:37:54.0000000Z",
        "time_open": "2018-09-03T00:37:39.0000000Z",
        "time_period_end": "2018-09-03T00:38:00.0000000Z",
        "time_period_start": "2018-09-03T00:37:00.0000000Z",
        "trades_count": 8,
        "volume_traded": 0.43616666
    },
    {
        "price_close": 7282.3,
        "price_high": 7282.3,
        "price_low": 7281.74,
        "price_open": 7281.74,
        "time_close": "2018-09-03T00:38:13.0000000Z",
        "time_open": "2018-09-03T00:38:00.0000000Z",
        "time_period_end": "2018-09-03T00:39:00.0000000Z",
        "time_period_start": "2018-09-03T00:38:00.0000000Z",
        "trades_count": 2,
        "volume_traded": 0.07835776
    },
    {
        "price_close": 7283.38,
        "price_high": 7283.38,
        "price_low": 7283.38,
        "price_open": 7283.38,
        "time_close": "2018-09-03T00:39:58.0000000Z",
        "time_open": "2018-09-03T00:39:40.0000000Z",
        "time_period_end": "2018-09-03T00:40:00.0000000Z",
        "time_period_start": "2018-09-03T00:39:00.0000000Z",
        "trades_count": 2,
        "volume_traded": 0.551
    },
    {
        "price_close": 7286.42,
        "price_high": 7286.42,
        "price_low": 7282.29,
        "price_open": 7283.38,
        "time_close": "2018-09-03T00:40:43.0000000Z",
        "time_open": "2018-09-03T00:40:03.0000000Z",
        "time_period_end": "2018-09-03T00:41:00.0000000Z",
        "time_period_start": "2018-09-03T00:40:00.0000000Z",
        "trades_count": 6,
        "volume_traded": 0.84734985
    },
    {
        "price_close": 7272.97,
        "price_high": 7287.26,
        "price_low": 7272.97,
        "price_open": 7287.26,
        "time_close": "2018-09-03T00:41:28.0000000Z",
        "time_open": "2018-09-03T00:41:22.0000000Z",
        "time_period_end": "2018-09-03T00:42:00.0000000Z",
        "time_period_start": "2018-09-03T00:41:00.0000000Z",
        "trades_count": 8,
        "volume_traded": 0.89945246
    },
    {
        "price_close": 7288.42,
        "price_high": 7288.42,
        "price_low": 7273.04,
        "price_open": 7278.07,
        "time_close": "2018-09-03T00:42:53.0000000Z",
        "time_open": "2018-09-03T00:42:07.0000000Z",
        "time_period_end": "2018-09-03T00:43:00.0000000Z",
        "time_period_start": "2018-09-03T00:42:00.0000000Z",
        "trades_count": 24,
        "volume_traded": 34.75826214
    },
    {
        "price_close": 7282.92,
        "price_high": 7282.92,
        "price_low": 7277.55,
        "price_open": 7277.55,
        "time_close": "2018-09-03T00:43:59.0000000Z",
        "time_open": "2018-09-03T00:43:17.0000000Z",
        "time_period_end": "2018-09-03T00:44:00.0000000Z",
        "time_period_start": "2018-09-03T00:43:00.0000000Z",
        "trades_count": 2,
        "volume_traded": 0.06729524
    },
    {
        "price_close": 7282.9,
        "price_high": 7282.9,
        "price_low": 7282.9,
        "price_open": 7282.9,
        "time_close": "2018-09-03T00:44:29.0000000Z",
        "time_open": "2018-09-03T00:44:29.0000000Z",
        "time_period_end": "2018-09-03T00:45:00.0000000Z",
        "time_period_start": "2018-09-03T00:44:00.0000000Z",
        "trades_count": 1,
        "volume_traded": 0.05
    },
    {
        "price_close": 7279.52,
        "price_high": 7279.52,
        "price_low": 7279.52,
        "price_open": 7279.52,
        "time_close": "2018-09-03T00:45:42.0000000Z",
        "time_open": "2018-09-03T00:45:42.0000000Z",
        "time_period_end": "2018-09-03T00:46:00.0000000Z",
        "time_period_start": "2018-09-03T00:45:00.0000000Z",
        "trades_count": 2,
        "volume_traded": 0.1018169
    },
    {
        "price_close": 7277.31,
        "price_high": 7277.31,
        "price_low": 7277.31,
        "price_open": 7277.31,
        "time_close": "2018-09-03T00:47:13.0000000Z",
        "time_open": "2018-09-03T00:47:13.0000000Z",
        "time_period_end": "2018-09-03T00:48:00.0000000Z",
        "time_period_start": "2018-09-03T00:47:00.0000000Z",
        "trades_count": 1,
        "volume_traded": 0.01115093
    },
    {
        "price_close": 7271.81,
        "price_high": 7275.51,
        "price_low": 7271.81,
        "price_open": 7275.51,
        "time_close": "2018-09-03T00:48:19.0000000Z",
        "time_open": "2018-09-03T00:48:10.0000000Z",
        "time_period_end": "2018-09-03T00:49:00.0000000Z",
        "time_period_start": "2018-09-03T00:48:00.0000000Z",
        "trades_count": 6,
        "volume_traded": 0.17984422
    },
    {
        "price_close": 7271.95,
        "price_high": 7271.95,
        "price_low": 7271.95,
        "price_open": 7271.95,
        "time_close": "2018-09-03T00:49:16.0000000Z",
        "time_open": "2018-09-03T00:49:16.0000000Z",
        "time_period_end": "2018-09-03T00:50:00.0000000Z",
        "time_period_start": "2018-09-03T00:49:00.0000000Z",
        "trades_count": 1,
        "volume_traded": 0.0011724
    },
    {
        "price_close": 7268.07,
        "price_high": 7268.07,
        "price_low": 7256.82,
        "price_open": 7267.01,
        "time_close": "2018-09-03T00:50:59.0000000Z",
        "time_open": "2018-09-03T00:50:39.0000000Z",
        "time_period_end": "2018-09-03T00:51:00.0000000Z",
        "time_period_start": "2018-09-03T00:50:00.0000000Z",
        "trades_count": 29,
        "volume_traded": 34.53095616
    },
    {
        "price_close": 7271.31,
        "price_high": 7271.31,
        "price_low": 7271.31,
        "price_open": 7271.31,
        "time_close": "2018-09-03T00:52:34.0000000Z",
        "time_open": "2018-09-03T00:52:34.0000000Z",
        "time_period_end": "2018-09-03T00:53:00.0000000Z",
        "time_period_start": "2018-09-03T00:52:00.0000000Z",
        "trades_count": 1,
        "volume_traded": 0.446
    },
    {
        "price_close": 7272.99,
        "price_high": 7272.99,
        "price_low": 7266.81,
        "price_open": 7266.81,
        "time_close": "2018-09-03T00:54:29.0000000Z",
        "time_open": "2018-09-03T00:54:06.0000000Z",
        "time_period_end": "2018-09-03T00:55:00.0000000Z",
        "time_period_start": "2018-09-03T00:54:00.0000000Z",
        "trades_count": 11,
        "volume_traded": 0.6651728
    },
    {
        "price_close": 7267.14,
        "price_high": 7274.99,
        "price_low": 7267.14,
        "price_open": 7274.99,
        "time_close": "2018-09-03T00:55:27.0000000Z",
        "time_open": "2018-09-03T00:55:11.0000000Z",
        "time_period_end": "2018-09-03T00:56:00.0000000Z",
        "time_period_start": "2018-09-03T00:55:00.0000000Z",
        "trades_count": 4,
        "volume_traded": 0.12433473
    },
    {
        "price_close": 7276.59,
        "price_high": 7276.59,
        "price_low": 7272.2,
        "price_open": 7274.29,
        "time_close": "2018-09-03T00:56:21.0000000Z",
        "time_open": "2018-09-03T00:56:03.0000000Z",
        "time_period_end": "2018-09-03T00:57:00.0000000Z",
        "time_period_start": "2018-09-03T00:56:00.0000000Z",
        "trades_count": 15,
        "volume_traded": 3.30058165
    },
    {
        "price_close": 7276.99,
        "price_high": 7276.99,
        "price_low": 7268.68,
        "price_open": 7271.87,
        "time_close": "2018-09-03T00:57:50.0000000Z",
        "time_open": "2018-09-03T00:57:09.0000000Z",
        "time_period_end": "2018-09-03T00:58:00.0000000Z",
        "time_period_start": "2018-09-03T00:57:00.0000000Z",
        "trades_count": 19,
        "volume_traded": 1.04776305
    },
    {
        "price_close": 7276.99,
        "price_high": 7276.99,
        "price_low": 7276.99,
        "price_open": 7276.99,
        "time_close": "2018-09-03T00:58:48.0000000Z",
        "time_open": "2018-09-03T00:58:48.0000000Z",
        "time_period_end": "2018-09-03T00:59:00.0000000Z",
        "time_period_start": "2018-09-03T00:58:00.0000000Z",
        "trades_count": 1,
        "volume_traded": 0.00099725
    },
    {
        "price_close": 7271.74,
        "price_high": 7274.44,
        "price_low": 7271.74,
        "price_open": 7274.44,
        "time_close": "2018-09-03T00:59:39.0000000Z",
        "time_open": "2018-09-03T00:59:36.0000000Z",
        "time_period_end": "2018-09-03T01:00:00.0000000Z",
        "time_period_start": "2018-09-03T00:59:00.0000000Z",
        "trades_count": 2,
        "volume_traded": 0.12745
    },
    {
        "price_close": 7275.64,
        "price_high": 7277.2,
        "price_low": 7270.63,
        "price_open": 7277.2,
        "time_close": "2018-09-03T01:00:50.0000000Z",
        "time_open": "2018-09-03T01:00:02.0000000Z",
        "time_period_end": "2018-09-03T01:01:00.0000000Z",
        "time_period_start": "2018-09-03T01:00:00.0000000Z",
        "trades_count": 4,
        "volume_traded": 0.26260757
    },
    {
        "price_close": 7271.0,
        "price_high": 7278.02,
        "price_low": 7271.0,
        "price_open": 7277.99,
        "time_close": "2018-09-03T01:01:57.0000000Z",
        "time_open": "2018-09-03T01:01:04.0000000Z",
        "time_period_end": "2018-09-03T01:02:00.0000000Z",
        "time_period_start": "2018-09-03T01:01:00.0000000Z",
        "trades_count": 4,
        "volume_traded": 1.10436016
    },
    {
        "price_close": 7272.1,
        "price_high": 7272.1,
        "price_low": 7272.1,
        "price_open": 7272.1,
        "time_close": "2018-09-03T01:02:19.0000000Z",
        "time_open": "2018-09-03T01:02:19.0000000Z",
        "time_period_end": "2018-09-03T01:03:00.0000000Z",
        "time_period_start": "2018-09-03T01:02:00.0000000Z",
        "trades_count": 1,
        "volume_traded": 0.00098873
    },
    {
        "price_close": 7274.37,
        "price_high": 7274.37,
        "price_low": 7274.37,
        "price_open": 7274.37,
        "time_close": "2018-09-03T01:03:56.0000000Z",
        "time_open": "2018-09-03T01:03:56.0000000Z",
        "time_period_end": "2018-09-03T01:04:00.0000000Z",
        "time_period_start": "2018-09-03T01:03:00.0000000Z",
        "trades_count": 1,
        "volume_traded": 0.0027425
    },
    {
        "price_close": 7276.99,
        "price_high": 7276.99,
        "price_low": 7273.15,
        "price_open": 7273.15,
        "time_close": "2018-09-03T01:05:12.0000000Z",
        "time_open": "2018-09-03T01:05:03.0000000Z",
        "time_period_end": "2018-09-03T01:06:00.0000000Z",
        "time_period_start": "2018-09-03T01:05:00.0000000Z",
        "trades_count": 4,
        "volume_traded": 0.08952
    },
    {
        "price_close": 7274.21,
        "price_high": 7274.21,
        "price_low": 7274.21,
        "price_open": 7274.21,
        "time_close": "2018-09-03T01:06:01.0000000Z",
        "time_open": "2018-09-03T01:06:01.0000000Z",
        "time_period_end": "2018-09-03T01:07:00.0000000Z",
        "time_period_start": "2018-09-03T01:06:00.0000000Z",
        "trades_count": 1,
        "volume_traded": 0.00385017
    },
    {
        "price_close": 7273.05,
        "price_high": 7273.06,
        "price_low": 7273.04,
        "price_open": 7273.04,
        "time_close": "2018-09-03T01:08:49.0000000Z",
        "time_open": "2018-09-03T01:08:39.0000000Z",
        "time_period_end": "2018-09-03T01:09:00.0000000Z",
        "time_period_start": "2018-09-03T01:08:00.0000000Z",
        "trades_count": 3,
        "volume_traded": 0.1139
    },
    {
        "price_close": 7266.4,
        "price_high": 7273.02,
        "price_low": 7266.4,
        "price_open": 7273.02,
        "time_close": "2018-09-03T01:09:50.0000000Z",
        "time_open": "2018-09-03T01:09:49.0000000Z",
        "time_period_end": "2018-09-03T01:10:00.0000000Z",
        "time_period_start": "2018-09-03T01:09:00.0000000Z",
        "trades_count": 3,
        "volume_traded": 1.01090723
    },
    {
        "price_close": 7255.0,
        "price_high": 7261.46,
        "price_low": 7252.2,
        "price_open": 7260.0,
        "time_close": "2018-09-03T01:11:58.0000000Z",
        "time_open": "2018-09-03T01:11:38.0000000Z",
        "time_period_end": "2018-09-03T01:12:00.0000000Z",
        "time_period_start": "2018-09-03T01:11:00.0000000Z",
        "trades_count": 25,
        "volume_traded": 18.87582088
    },
    {
        "price_close": 7263.24,
        "price_high": 7266.99,
        "price_low": 7254.86,
        "price_open": 7254.97,
        "time_close": "2018-09-03T01:12:53.0000000Z",
        "time_open": "2018-09-03T01:12:00.0000000Z",
        "time_period_end": "2018-09-03T01:13:00.0000000Z",
        "time_period_start": "2018-09-03T01:12:00.0000000Z",
        "trades_count": 42,
        "volume_traded": 10.81901919
    },
    {
        "price_close": 7263.99,
        "price_high": 7266.85,
        "price_low": 7263.23,
        "price_open": 7263.24,
        "time_close": "2018-09-03T01:13:44.0000000Z",
        "time_open": "2018-09-03T01:13:06.0000000Z",
        "time_period_end": "2018-09-03T01:14:00.0000000Z",
        "time_period_start": "2018-09-03T01:13:00.0000000Z",
        "trades_count": 13,
        "volume_traded": 0.16549004
    },
    {
        "price_close": 7261.55,
        "price_high": 7263.24,
        "price_low": 7253.92,
        "price_open": 7263.24,
        "time_close": "2018-09-03T01:14:59.0000000Z",
        "time_open": "2018-09-03T01:14:27.0000000Z",
        "time_period_end": "2018-09-03T01:15:00.0000000Z",
        "time_period_start": "2018-09-03T01:14:00.0000000Z",
        "trades_count": 12,
        "volume_traded": 2.28722216
    },
    {
        "price_close": 7256.25,
        "price_high": 7260.08,
        "price_low": 7250.99,
        "price_open": 7260.08,
        "time_close": "2018-09-03T01:15:59.0000000Z",
        "time_open": "2018-09-03T01:15:00.0000000Z",
        "time_period_end": "2018-09-03T01:16:00.0000000Z",
        "time_period_start": "2018-09-03T01:15:00.0000000Z",
        "trades_count": 45,
        "volume_traded": 30.18960932
    },
    {
        "price_close": 7251.85,
        "price_high": 7253.72,
        "price_low": 7247.86,
        "price_open": 7253.72,
        "time_close": "2018-09-03T01:16:58.0000000Z",
        "time_open": "2018-09-03T01:16:05.0000000Z",
        "time_period_end": "2018-09-03T01:17:00.0000000Z",
        "time_period_start": "2018-09-03T01:16:00.0000000Z",
        "trades_count": 22,
        "volume_traded": 9.53839755
    },
    {
        "price_close": 7251.17,
        "price_high": 7255.02,
        "price_low": 7247.86,
        "price_open": 7255.02,
        "time_close": "2018-09-03T01:17:55.0000000Z",
        "time_open": "2018-09-03T01:17:09.0000000Z",
        "time_period_end": "2018-09-03T01:18:00.0000000Z",
        "time_period_start": "2018-09-03T01:17:00.0000000Z",
        "trades_count": 17,
        "volume_traded": 11.49223342
    },
    {
        "price_close": 7244.69,
        "price_high": 7254.81,
        "price_low": 7244.69,
        "price_open": 7248.28,
        "time_close": "2018-09-03T01:18:38.0000000Z",
        "time_open": "2018-09-03T01:18:06.0000000Z",
        "time_period_end": "2018-09-03T01:19:00.0000000Z",
        "time_period_start": "2018-09-03T01:18:00.0000000Z",
        "trades_count": 9,
        "volume_traded": 5.03402067
    },
    {
        "price_close": 7253.55,
        "price_high": 7253.83,
        "price_low": 7237.07,
        "price_open": 7242.26,
        "time_close": "2018-09-03T01:19:50.0000000Z",
        "time_open": "2018-09-03T01:19:02.0000000Z",
        "time_period_end": "2018-09-03T01:20:00.0000000Z",
        "time_period_start": "2018-09-03T01:19:00.0000000Z",
        "trades_count": 47,
        "volume_traded": 40.47320682
    },
    {
        "price_close": 7252.71,
        "price_high": 7252.71,
        "price_low": 7250.9,
        "price_open": 7250.9,
        "time_close": "2018-09-03T01:20:34.0000000Z",
        "time_open": "2018-09-03T01:20:20.0000000Z",
        "time_period_end": "2018-09-03T01:21:00.0000000Z",
        "time_period_start": "2018-09-03T01:20:00.0000000Z",
        "trades_count": 4,
        "volume_traded": 0.07897698
    },
    {
        "price_close": 7252.39,
        "price_high": 7252.39,
        "price_low": 7240.12,
        "price_open": 7247.55,
        "time_close": "2018-09-03T01:22:20.0000000Z",
        "time_open": "2018-09-03T01:22:15.0000000Z",
        "time_period_end": "2018-09-03T01:23:00.0000000Z",
        "time_period_start": "2018-09-03T01:22:00.0000000Z",
        "trades_count": 5,
        "volume_traded": 2.80145612
    },
    {
        "price_close": 7247.68,
        "price_high": 7252.39,
        "price_low": 7247.68,
        "price_open": 7252.39,
        "time_close": "2018-09-03T01:24:34.0000000Z",
        "time_open": "2018-09-03T01:24:21.0000000Z",
        "time_period_end": "2018-09-03T01:25:00.0000000Z",
        "time_period_start": "2018-09-03T01:24:00.0000000Z",
        "trades_count": 3,
        "volume_traded": 0.09461955
    },
    {
        "price_close": 7247.68,
        "price_high": 7247.68,
        "price_low": 7247.68,
        "price_open": 7247.68,
        "time_close": "2018-09-03T01:25:10.0000000Z",
        "time_open": "2018-09-03T01:25:09.0000000Z",
        "time_period_end": "2018-09-03T01:26:00.0000000Z",
        "time_period_start": "2018-09-03T01:25:00.0000000Z",
        "trades_count": 2,
        "volume_traded": 0.00117182
    },
    {
        "price_close": 7252.71,
        "price_high": 7252.71,
        "price_low": 7252.71,
        "price_open": 7252.71,
        "time_close": "2018-09-03T01:26:13.0000000Z",
        "time_open": "2018-09-03T01:26:13.0000000Z",
        "time_period_end": "2018-09-03T01:27:00.0000000Z",
        "time_period_start": "2018-09-03T01:26:00.0000000Z",
        "trades_count": 1,
        "volume_traded": 0.01596376
    },
    {
        "price_close": 7252.7,
        "price_high": 7252.7,
        "price_low": 7251.41,
        "price_open": 7252.7,
        "time_close": "2018-09-03T01:28:22.0000000Z",
        "time_open": "2018-09-03T01:28:01.0000000Z",
        "time_period_end": "2018-09-03T01:29:00.0000000Z",
        "time_period_start": "2018-09-03T01:28:00.0000000Z",
        "trades_count": 3,
        "volume_traded": 0.12350165
    },
    {
        "price_close": 7242.0,
        "price_high": 7251.4,
        "price_low": 7242.0,
        "price_open": 7251.4,
        "time_close": "2018-09-03T01:29:59.0000000Z",
        "time_open": "2018-09-03T01:29:11.0000000Z",
        "time_period_end": "2018-09-03T01:30:00.0000000Z",
        "time_period_start": "2018-09-03T01:29:00.0000000Z",
        "trades_count": 8,
        "volume_traded": 2.98812725
    },
    {
        "price_close": 7245.01,
        "price_high": 7247.16,
        "price_low": 7237.07,
        "price_open": 7241.23,
        "time_close": "2018-09-03T01:30:55.0000000Z",
        "time_open": "2018-09-03T01:30:00.0000000Z",
        "time_period_end": "2018-09-03T01:31:00.0000000Z",
        "time_period_start": "2018-09-03T01:30:00.0000000Z",
        "trades_count": 23,
        "volume_traded": 14.39725384
    },
    {
        "price_close": 7245.01,
        "price_high": 7245.01,
        "price_low": 7245.0,
        "price_open": 7245.0,
        "time_close": "2018-09-03T01:31:50.0000000Z",
        "time_open": "2018-09-03T01:31:15.0000000Z",
        "time_period_end": "2018-09-03T01:32:00.0000000Z",
        "time_period_start": "2018-09-03T01:31:00.0000000Z",
        "trades_count": 3,
        "volume_traded": 0.99795874
    },
    {
        "price_close": 7247.34,
        "price_high": 7247.45,
        "price_low": 7245.01,
        "price_open": 7245.01,
        "time_close": "2018-09-03T01:32:59.0000000Z",
        "time_open": "2018-09-03T01:32:04.0000000Z",
        "time_period_end": "2018-09-03T01:33:00.0000000Z",
        "time_period_start": "2018-09-03T01:32:00.0000000Z",
        "trades_count": 18,
        "volume_traded": 1.21866695
    },
    {
        "price_close": 7250.78,
        "price_high": 7250.78,
        "price_low": 7247.44,
        "price_open": 7247.44,
        "time_close": "2018-09-03T01:33:59.0000000Z",
        "time_open": "2018-09-03T01:33:09.0000000Z",
        "time_period_end": "2018-09-03T01:34:00.0000000Z",
        "time_period_start": "2018-09-03T01:33:00.0000000Z",
        "trades_count": 20,
        "volume_traded": 0.554284
    },
    {
        "price_close": 7255.38,
        "price_high": 7255.39,
        "price_low": 7250.99,
        "price_open": 7250.99,
        "time_close": "2018-09-03T01:34:53.0000000Z",
        "time_open": "2018-09-03T01:34:00.0000000Z",
        "time_period_end": "2018-09-03T01:35:00.0000000Z",
        "time_period_start": "2018-09-03T01:34:00.0000000Z",
        "trades_count": 24,
        "volume_traded": 1.881721
    },
    {
        "price_close": 7255.39,
        "price_high": 7255.39,
        "price_low": 7255.39,
        "price_open": 7255.39,
        "time_close": "2018-09-03T01:36:17.0000000Z",
        "time_open": "2018-09-03T01:36:17.0000000Z",
        "time_period_end": "2018-09-03T01:37:00.0000000Z",
        "time_period_start": "2018-09-03T01:36:00.0000000Z",
        "trades_count": 1,
        "volume_traded": 0.00140896
    },
    {
        "price_close": 7255.39,
        "price_high": 7255.39,
        "price_low": 7255.39,
        "price_open": 7255.39,
        "time_close": "2018-09-03T01:37:45.0000000Z",
        "time_open": "2018-09-03T01:37:45.0000000Z",
        "time_period_end": "2018-09-03T01:38:00.0000000Z",
        "time_period_start": "2018-09-03T01:37:00.0000000Z",
        "trades_count": 1,
        "volume_traded": 0.001
    },
    {
        "price_close": 7255.39,
        "price_high": 7255.39,
        "price_low": 7255.39,
        "price_open": 7255.39,
        "time_close": "2018-09-03T01:38:13.0000000Z",
        "time_open": "2018-09-03T01:38:13.0000000Z",
        "time_period_end": "2018-09-03T01:39:00.0000000Z",
        "time_period_start": "2018-09-03T01:38:00.0000000Z",
        "trades_count": 1,
        "volume_traded": 0.0014387
    },
    {
        "price_close": 7254.99,
        "price_high": 7254.99,
        "price_low": 7254.85,
        "price_open": 7254.85,
        "time_close": "2018-09-03T01:40:17.0000000Z",
        "time_open": "2018-09-03T01:40:03.0000000Z",
        "time_period_end": "2018-09-03T01:41:00.0000000Z",
        "time_period_start": "2018-09-03T01:40:00.0000000Z",
        "trades_count": 2,
        "volume_traded": 0.00417578
    },
    {
        "price_close": 7250.21,
        "price_high": 7258.02,
        "price_low": 7250.21,
        "price_open": 7255.39,
        "time_close": "2018-09-03T01:41:41.0000000Z",
        "time_open": "2018-09-03T01:41:07.0000000Z",
        "time_period_end": "2018-09-03T01:42:00.0000000Z",
        "time_period_start": "2018-09-03T01:41:00.0000000Z",
        "trades_count": 20,
        "volume_traded": 2.17181103
    },
    {
        "price_close": 7258.02,
        "price_high": 7258.02,
        "price_low": 7257.77,
        "price_open": 7258.02,
        "time_close": "2018-09-03T01:42:53.0000000Z",
        "time_open": "2018-09-03T01:42:23.0000000Z",
        "time_period_end": "2018-09-03T01:43:00.0000000Z",
        "time_period_start": "2018-09-03T01:42:00.0000000Z",
        "trades_count": 4,
        "volume_traded": 0.24384372
    },
    {
        "price_close": 7258.02,
        "price_high": 7258.02,
        "price_low": 7258.02,
        "price_open": 7258.02,
        "time_close": "2018-09-03T01:43:25.0000000Z",
        "time_open": "2018-09-03T01:43:25.0000000Z",
        "time_period_end": "2018-09-03T01:44:00.0000000Z",
        "time_period_start": "2018-09-03T01:43:00.0000000Z",
        "trades_count": 1,
        "volume_traded": 0.00101758
    },
    {
        "price_close": 7258.02,
        "price_high": 7258.02,
        "price_low": 7257.77,
        "price_open": 7257.77,
        "time_close": "2018-09-03T01:44:35.0000000Z",
        "time_open": "2018-09-03T01:44:32.0000000Z",
        "time_period_end": "2018-09-03T01:45:00.0000000Z",
        "time_period_start": "2018-09-03T01:44:00.0000000Z",
        "trades_count": 3,
        "volume_traded": 0.05423327
    },
    {
        "price_close": 7258.99,
        "price_high": 7258.99,
        "price_low": 7258.99,
        "price_open": 7258.99,
        "time_close": "2018-09-03T01:45:48.0000000Z",
        "time_open": "2018-09-03T01:45:47.0000000Z",
        "time_period_end": "2018-09-03T01:46:00.0000000Z",
        "time_period_start": "2018-09-03T01:45:00.0000000Z",
        "trades_count": 10,
        "volume_traded": 0.01983428
    },
    {
        "price_close": 7258.99,
        "price_high": 7258.99,
        "price_low": 7258.99,
        "price_open": 7258.99,
        "time_close": "2018-09-03T01:46:15.0000000Z",
        "time_open": "2018-09-03T01:46:15.0000000Z",
        "time_period_end": "2018-09-03T01:47:00.0000000Z",
        "time_period_start": "2018-09-03T01:46:00.0000000Z",
        "trades_count": 1,
        "volume_traded": 0.078
    },
    {
        "price_close": 7258.5,
        "price_high": 7258.5,
        "price_low": 7258.5,
        "price_open": 7258.5,
        "time_close": "2018-09-03T01:47:57.0000000Z",
        "time_open": "2018-09-03T01:47:57.0000000Z",
        "time_period_end": "2018-09-03T01:48:00.0000000Z",
        "time_period_start": "2018-09-03T01:47:00.0000000Z",
        "trades_count": 1,
        "volume_traded": 0.10521026
    },
    {
        "price_close": 7259.99,
        "price_high": 7259.99,
        "price_low": 7258.98,
        "price_open": 7258.98,
        "time_close": "2018-09-03T01:48:19.0000000Z",
        "time_open": "2018-09-03T01:48:18.0000000Z",
        "time_period_end": "2018-09-03T01:49:00.0000000Z",
        "time_period_start": "2018-09-03T01:48:00.0000000Z",
        "trades_count": 13,
        "volume_traded": 0.11334278
    },
    {
        "price_close": 7261.64,
        "price_high": 7261.64,
        "price_low": 7261.58,
        "price_open": 7261.58,
        "time_close": "2018-09-03T01:49:58.0000000Z",
        "time_open": "2018-09-03T01:49:47.0000000Z",
        "time_period_end": "2018-09-03T01:50:00.0000000Z",
        "time_period_start": "2018-09-03T01:49:00.0000000Z",
        "trades_count": 4,
        "volume_traded": 1.07662055
    },
    {
        "price_close": 7261.64,
        "price_high": 7261.64,
        "price_low": 7261.64,
        "price_open": 7261.64,
        "time_close": "2018-09-03T01:50:42.0000000Z",
        "time_open": "2018-09-03T01:50:41.0000000Z",
        "time_period_end": "2018-09-03T01:51:00.0000000Z",
        "time_period_start": "2018-09-03T01:50:00.0000000Z",
        "trades_count": 2,
        "volume_traded": 0.03528542
    },
    {
        "price_close": 7261.99,
        "price_high": 7261.99,
        "price_low": 7261.99,
        "price_open": 7261.99,
        "time_close": "2018-09-03T01:51:33.0000000Z",
        "time_open": "2018-09-03T01:51:32.0000000Z",
        "time_period_end": "2018-09-03T01:52:00.0000000Z",
        "time_period_start": "2018-09-03T01:51:00.0000000Z",
        "trades_count": 11,
        "volume_traded": 0.01610954
    },
    {
        "price_close": 7258.11,
        "price_high": 7263.48,
        "price_low": 7258.11,
        "price_open": 7263.48,
        "time_close": "2018-09-03T01:55:25.0000000Z",
        "time_open": "2018-09-03T01:55:08.0000000Z",
        "time_period_end": "2018-09-03T01:56:00.0000000Z",
        "time_period_start": "2018-09-03T01:55:00.0000000Z",
        "trades_count": 6,
        "volume_traded": 1.35784395
    },
    {
        "price_close": 7258.12,
        "price_high": 7258.12,
        "price_low": 7258.12,
        "price_open": 7258.12,
        "time_close": "2018-09-03T01:57:45.0000000Z",
        "time_open": "2018-09-03T01:57:45.0000000Z",
        "time_period_end": "2018-09-03T01:58:00.0000000Z",
        "time_period_start": "2018-09-03T01:57:00.0000000Z",
        "trades_count": 1,
        "volume_traded": 0.00121
    }
]