[
    {
        "price_close": 9820.0,
        "price_high": 9820.0,
        "price_low": 9809.91,
        "price_open": 9809.91,
        "time_close": "2020-05-15T00:00:51.9620000Z",
        "time_open": "2020-05-15T00:00:36.3090000Z",
        "time_period_end": "2020-05-15T00:01:00.0000000Z",
        "time_period_start": "2020-05-15T00:00:00.0000000Z",
        "trades_count": 14,
        "volume_traded": 11.83716847
    },
    {
        "price_close": 9836.79,
        "price_high": 9844.66,
        "price_low": 9814.04,
        "price_open": 9821.07,
        "time_close": "2020-05-15T00:01:58.7040000Z",
        "time_open": "2020-05-15T00:01:02.7420000Z",
        "time_period_end": "2020-05-15T00:02:00.0000000Z",
        "time_period_start": "2020-05-15T00:01:00.0000000Z",
        "trades_count": 76,
        "volume_traded": 20.2125228
    },
    {
        "price_close": 9834.0,
        "price_high": 9838.76,
        "price_low": 9829.13,
        "price_open": 9834.98,
        "time_close": "2020-05-15T00:02:49.2700000Z",
        "time_open": "2020-05-15T00:02:12.8750000Z",
        "time_period_end": "2020-05-15T00:03:00.0000000Z",
        "time_period_start": "2020-05-15T00:02:00.0000000Z",
        "trades_count": 9,
        "volume_traded": 0.63901969
    },
    {
        "price_close": 9830.63,
        "price_high": 9842.85,
        "price_low": 9826.9,
        "price_open": 9837.0,
        "time_close": "2020-05-15T00:03:54.0140000Z",
        "time_open": "2020-05-15T00:03:07.5600000Z",
        "time_period_end": "2020-05-15T00:04:00.0000000Z",
        "time_period_start": "2020-05-15T00:03:00.0000000Z",
        "trades_count": 26,
        "volume_traded": 2.29505666
    },
    {
        "price_close": 9825.94,
        "price_high": 9830.82,
        "price_low": 9820.69,
        "price_open": 9830.82,
        "time_close": "2020-05-15T00:04:29.4770000Z",
        "time_open": "2020-05-15T00:04:06.3100000Z",
        "time_period_end": "2020-05-15T00:05:00.0000000Z",
        "time_period_start": "2020-05-15T00:04:00.0000000Z",
        "trades_count": 3,
        "volume_traded": 0.02364506
    },
    {
        "price_close": 9783.86,
        "price_high": 9825.7,
        "price_low": 9783.86,
        "price_open": 9819.9,
        "time_close": "2020-05-15T00:05:51.3650000Z",
        "time_open": "2020-05-15T00:05:06.5290000Z",
        "time_period_end": "2020-05-15T00:06:00.0000000Z",
        "time_period_start": "2020-05-15T00:05:00.0000000Z",
        "trades_count": 45,
        "volume_traded": 52.37316685
    },
    {
        "price_close": 9766.0,
        "price_high": 9800.06,
        "price_low": 9766.0,
        "price_open": 9793.84,
        "time_close": "2020-05-15T00:06:59.8210000Z",
        "time_open": "2020-05-15T00:06:01.1210000Z",
        "time_period_end": "2020-05-15T00:07:00.0000000Z",
        "time_period_start": "2020-05-15T00:06:00.0000000Z",
        "trades_count": 29,
        "volume_traded": 36.13177046
    },
    {
        "price_close": 9771.26,
        "price_high": 9792.7,
        "price_low": 9760.02,
        "price_open": 9766.0,
        "time_close": "2020-05-15T00:07:51.2910000Z",
        "time_open": "2020-05-15T00:07:00.1290000Z",
        "time_period_end": "2020-05-15T00:08:00.0000000Z",
        "time_period_start": "2020-05-15T00:07:00.0000000Z",
        "trades_count": 74,
        "volume_traded": 21.48784279
    },
    {
        "price_close": 9782.29,
        "price_high": 9786.53,
        "price_low": 9766.49,
        "price_open": 9766.49,
        "time_close": "2020-05-15T00:08:47.6170000Z",
        "time_open": "2020-05-15T00:08:10.9320000Z",
        "time_period_end": "2020-05-15T00:09:00.0000000Z",
        "time_period_start": "2020-05-15T00:08:00.0000000Z",
        "trades_count": 24,
        "volume_traded": 1.39981088
    },
    {
        "price_close": 9777.19,
        "price_high": 9782.28,
        "price_low": 9768.49,
        "price_open": 9782.28,
        "time_close": "2020-05-15T00:09:35.8400000Z",
        "time_open": "2020-05-15T00:09:03.8130000Z",
        "time_period_end": "2020-05-15T00:10:00.0000000Z",
        "time_period_start": "2020-05-15T00:09:00.0000000Z",
        "trades_count": 6,
        "volume_traded": 0.42553696
    },
    {
        "price_close": 9783.61,
        "price_high": 9783.62,
        "price_low": 9778.14,
        "price_open": 9778.14,
        "time_close": "2020-05-15T00:10:59.4750000Z",
        "time_open": "2020-05-15T00:10:12.0830000Z",
        "time_period_end": "2020-05-15T00:11:00.0000000Z",
        "time_period_start": "2020-05-15T00:10:00.0000000Z",
        "trades_count": 26,
        "volume_traded": 5.21578704
    },
    {
        "price_close": 9782.19,
        "price_high": 9788.62,
        "price_low": 9776.14,
        "price_open": 9779.89,
        "time_close": "2020-05-15T00:11:58.9260000Z",
        "time_open": "2020-05-15T00:11:01.2230000Z",
        "time_period_end": "2020-05-15T00:12:00.0000000Z",
        "time_period_start": "2020-05-15T00:11:00.0000000Z",
        "trades_count": 61,
        "volume_traded": 1.30388457
    },
    {
        "price_close": 9760.25,
        "price_high": 9789.59,
        "price_low": 9760.0,
        "price_open": 9782.19,
        "time_close": "2020-05-15T00:12:54.9340000Z",
        "time_open": "2020-05-15T00:12:01.9480000Z",
        "time_period_end": "2020-05-15T00:13:00.0000000Z",
        "time_period_start": "2020-05-15T00:12:00.0000000Z",
        "trades_count": 71,
        "volume_traded": 9.44590882
    },
    {
        "price_close": 9755.65,
        "price_high": 9771.65,
        "price_low": 9755.65,
        "price_open": 9763.42,
        "time_close": "2020-05-15T00:13:51.9920000Z",
        "time_open": "2020-05-15T00:13:08.0130000Z",
        "time_period_end": "2020-05-15T00:14:00.0000000Z",
        "time_period_start": "2020-05-15T00:13:00.0000000Z",
        "trades_count": 73,
        "volume_traded": 17.41754358
    },
    {
        "price_close": 9764.38,
        "price_high": 9764.38,
        "price_low": 9750.0,
        "price_open": 9754.97,
        "time_close": "2020-05-15T00:14:56.4060000Z",
        "time_open": "2020-05-15T00:14:02.4650000Z",
        "time_period_end": "2020-05-15T00:15:00.0000000Z",
        "time_period_start": "2020-05-15T00:14:00.0000000Z",
        "trades_count": 59,
        "volume_traded": 117.79752937
    },
    {
        "price_close": 9756.48,
        "price_high": 9766.24,
        "price_low": 9754.65,
        "price_open": 9761.21,
        "time_close": "2020-05-15T00:15:47.4510000Z",
        "time_open": "2020-05-15T00:15:05.5670000Z",
        "time_period_end": "2020-05-15T00:16:00.0000000Z",
        "time_period_start": "2020-05-15T00:15:00.0000000Z",
        "trades_count": 29,
        "volume_traded": 3.34694618
    },
    {
        "price_close": 9743.5,
        "price_high": 9759.32,
        "price_low": 9738.94,
        "price_open": 9759.27,
        "time_close": "2020-05-15T00:16:55.0780000Z",
        "time_open": "2020-05-15T00:16:03.7430000Z",
        "time_period_end": "2020-05-15T00:17:00.0000000Z",
        "time_period_start": "2020-05-15T00:16:00.0000000Z",
        "trades_count": 61,
        "volume_traded": 11.49302238
    },
    {
        "price_close": 9745.2,
        "price_high": 9749.8,
        "price_low": 9744.78,
        "price_open": 9748.03,
        "time_close": "2020-05-15T00:17:56.9370000Z",
        "time_open": "2020-05-15T00:17:01.3330000Z",
        "time_period_end": "2020-05-15T00:18:00.0000000Z",
        "time_period_start": "2020-05-15T00:17:00.0000000Z",
        "trades_count": 17,
        "volume_traded": 2.66897289
    },
    {
        "price_close": 9739.06,
        "price_high": 9749.19,
        "price_low": 9739.06,
        "price_open": 9749.19,
        "time_close": "2020-05-15T00:18:55.9990000Z",
        "time_open": "2020-05-15T00:18:09.2100000Z",
        "time_period_end": "2020-05-15T00:19:00.0000000Z",
        "time_period_start": "2020-05-15T00:18:00.0000000Z",
        "trades_count": 31,
        "volume_traded": 4.84698043
    },
    {
        "price_close": 9735.0,
        "price_high": 9740.0,
        "price_low": 9727.27,
        "price_open": 9738.22,
        "time_close": "2020-05-15T00:19:52.4430000Z",
        "time_open": "2020-05-15T00:19:02.0980000Z",
        "time_period_end": "2020-05-15T00:20:00.0000000Z",
        "time_period_start": "2020-05-15T00:19:00.0000000Z",
        "trades_count": 61,
        "volume_traded": 12.1586447
    },
    {
        "price_close": 9723.06,
        "price_high": 9733.55,
        "price_low": 9714.14,
        "price_open": 9727.51,
        "time_close": "2020-05-15T00:20:55.9790000Z",
        "time_open": "2020-05-15T00:20:04.1490000Z",
        "time_period_end": "2020-05-15T00:21:00.0000000Z",
        "time_period_start": "2020-05-15T00:20:00.0000000Z",
        "trades_count": 88,
        "volume_traded": 29.87380343
    },
    {
        "price_close": 9729.92,
        "price_high": 9730.0,
        "price_low": 9722.93,
        "price_open": 9724.83,
        "time_close": "2020-05-15T00:21:49.7090000Z",
        "time_open": "2020-05-15T00:21:10.5660000Z",
        "time_period_end": "2020-05-15T00:22:00.0000000Z",
        "time_period_start": "2020-05-15T00:21:00.0000000Z",
        "trades_count": 7,
        "volume_traded": 0.11886851
    },
    {
        "price_close": 9732.48,
        "price_high": 9732.48,
        "price_low": 9718.46,
        "price_open": 9728.79,
        "time_close": "2020-05-15T00:22:52.0500000Z",
        "time_open": "2020-05-15T00:22:17.6090000Z",
        "time_period_end": "2020-05-15T00:23:00.0000000Z",
        "time_period_start": "2020-05-15T00:22:00.0000000Z",
        "trades_count": 8,
        "volume_traded": 1.14443983
    },
    {
        "price_close": 9750.59,
        "price_high": 9750.95,
        "price_low": 9733.46,
        "price_open": 9738.94,
        "time_close": "2020-05-15T00:23:58.8690000Z",
        "time_open": "2020-05-15T00:23:04.6960000Z",
        "time_period_end": "2020-05-15T00:24:00.0000000Z",
        "time_period_start": "2020-05-15T00:23:00.0000000Z",
        "trades_count": 21,
        "volume_traded": 9.58472932
    },
    {
        "price_close": 9746.09,
        "price_high": 9754.38,
        "price_low": 9742.42,
        "price_open": 9750.59,
        "time_close": "2020-05-15T00:24:56.9330000Z",
        "time_open": "2020-05-15T00:24:08.4540000Z",
        "time_period_end": "2020-05-15T00:25:00.0000000Z",
        "time_period_start": "2020-05-15T00:24:00.0000000Z",
        "trades_count": 13,
        "volume_traded": 1.20435136
    },
    {
        "price_close": 9752.85,
        "price_high": 9756.48,
        "price_low": 9744.23,
        "price_open": 9750.63,
        "time_close": "2020-05-15T00:25:58.8950000Z",
        "time_open": "2020-05-15T00:25:09.7940000Z",
        "time_period_end": "2020-05-15T00:26:00.0000000Z",
        "time_period_start": "2020-05-15T00:25:00.0000000Z",
        "trades_count": 13,
        "volume_traded": 2.76978942
    },
    {
        "price_close": 9742.56,
        "price_high": 9752.16,
        "price_low": 9742.56,
        "price_open": 9752.16,
        "time_close": "2020-05-15T00:26:42.0020000Z",
        "time_open": "2020-05-15T00:26:11.3240000Z",
        "time_period_end": "2020-05-15T00:27:00.0000000Z",
        "time_period_start": "2020-05-15T00:26:00.0000000Z",
        "trades_count": 5,
        "volume_traded": 1.15812486
    },
    {
        "price_close": 9754.76,
        "price_high": 9754.76,
        "price_low": 9744.43,
        "price_open": 9752.2,
        "time_close": "2020-05-15T00:27:43.7430000Z",
        "time_open": "2020-05-15T00:27:08.4090000Z",
        "time_period_end": "2020-05-15T00:28:00.0000000Z",
        "time_period_start": "2020-05-15T00:27:00.0000000Z",
        "trades_count": 4,
        "volume_traded": 0.1855378
    },
    {
        "price_close": 9755.16,
        "price_high": 9760.19,
        "price_low": 9746.35,
        "price_open": 9753.04,
        "time_close": "2020-05-15T00:28:59.4830000Z",
        "time_open": "2020-05-15T00:28:18.8420000Z",
        "time_period_end": "2020-05-15T00:29:00.0000000Z",
        "time_period_start": "2020-05-15T00:28:00.0000000Z",
        "trades_count": 17,
        "volume_traded": 1.90440451
    },
    {
        "price_close": 9740.72,
        "price_high": 9760.29,
        "price_low": 9740.72,
        "price_open": 9746.36,
        "time_close": "2020-05-15T00:29:54.1440000Z",
        "time_open": "2020-05-15T00:29:00.6030000Z",
        "time_period_end": "2020-05-15T00:30:00.0000000Z",
        "time_period_start": "2020-05-15T00:29:00.0000000Z",
        "trades_count": 15,
        "volume_traded": 3.94859454
    },
    {
        "price_close": 9735.72,
        "price_high": 9746.6,
        "price_low": 9735.3,
        "price_open": 9742.14,
        "time_close": "2020-05-15T00:30:56.1750000Z",
        "time_open": "2020-05-15T00:30:08.4880000Z",
        "time_period_end": "2020-05-15T00:31:00.0000000Z",
        "time_period_start": "2020-05-15T00:30:00.0000000Z",
        "trades_count": 8,
        "volume_traded": 0.51898374
    },
    {
        "price_close": 9750.67,
        "price_high": 9751.24,
        "price_low": 9743.32,
        "price_open": 9749.11,
        "time_close": "2020-05-15T00:31:58.0690000Z",
        "time_open": "2020-05-15T00:31:14.8570000Z",
        "time_period_end": "2020-05-15T00:32:00.0000000Z",
        "time_period_start": "2020-05-15T00:31:00.0000000Z",
        "trades_count": 9,
        "volume_traded": 3.6115004
    },
    {
        "price_close": 9745.03,
        "price_high": 9745.03,
        "price_low": 9744.86,
        "price_open": 9744.86,
        "time_close": "2020-05-15T00:32:56.2700000Z",
        "time_open": "2020-05-15T00:32:55.3160000Z",
        "time_period_end": "2020-05-15T00:33:00.0000000Z",
        "time_period_start": "2020-05-15T00:32:00.0000000Z",
        "trades_count": 2,
        "volume_traded": 0.01601566
    },
    {
        "price_close": 9760.28,
        "price_high": 9771.08,
        "price_low": 9753.68,
        "price_open": 9753.68,
        "time_close": "2020-05-15T00:33:58.1610000Z",
        "time_open": "2020-05-15T00:33:02.1090000Z",
        "time_period_end": "2020-05-15T00:34:00.0000000Z",
        "time_period_start": "2020-05-15T00:33:00.0000000Z",
        "trades_count": 22,
        "volume_traded": 5.45226479
    },
    {
        "price_close": 9766.4,
        "price_high": 9771.32,
        "price_low": 9760.4,
        "price_open": 9760.4,
        "time_close": "2020-05-15T00:34:56.5220000Z",
        "time_open": "2020-05-15T00:34:11.6570000Z",
        "time_period_end": "2020-05-15T00:35:00.0000000Z",
        "time_period_start": "2020-05-15T00:34:00.0000000Z",
        "trades_count": 5,
        "volume_traded": 0.12868801
    },
    {
        "price_close": 9770.73,
        "price_high": 9773.76,
        "price_low": 9764.41,
        "price_open": 9770.19,
        "time_close": "2020-05-15T00:35:59.9200000Z",
        "time_open": "2020-05-15T00:35:05.6320000Z",
        "time_period_end": "2020-05-15T00:36:00.0000000Z",
        "time_period_start": "2020-05-15T00:35:00.0000000Z",
        "trades_count": 14,
        "volume_traded": 1.22376995
    },
    {
        "price_close": 9779.91,
        "price_high": 9779.92,
        "price_low": 9766.19,
        "price_open": 9773.74,
        "time_close": "2020-05-15T00:36:52.1890000Z",
        "time_open": "2020-05-15T00:36:02.1990000Z",
        "time_period_end": "2020-05-15T00:37:00.0000000Z",
        "time_period_start": "2020-05-15T00:36:00.0000000Z",
        "trades_count": 17,
        "volume_traded": 10.9773499
    },
    {
        "price_close": 9779.92,
        "price_high": 9782.92,
        "price_low": 9775.0,
        "price_open": 9777.6,
        "time_close": "2020-05-15T00:37:43.0710000Z",
        "time_open": "2020-05-15T00:37:01.5240000Z",
        "time_period_end": "2020-05-15T00:38:00.0000000Z",
        "time_period_start": "2020-05-15T00:37:00.0000000Z",
        "trades_count": 15,
        "volume_traded": 1.33084458
    },
    {
        "price_close": 9764.91,
        "price_high": 9775.0,
        "price_low": 9764.57,
        "price_open": 9775.0,
        "time_close": "2020-05-15T00:38:56.5610000Z",
        "time_open": "2020-05-15T00:38:03.0030000Z",
        "time_period_end": "2020-05-15T00:39:00.0000000Z",
        "time_period_start": "2020-05-15T00:38:00.0000000Z",
        "trades_count": 28,
        "volume_traded": 49.71911373
    },
    {
        "price_close": 9771.02,
        "price_high": 9771.44,
        "price_low": 9764.37,
        "price_open": 9764.37,
        "time_close": "2020-05-15T00:39:36.3950000Z",
        "time_open": "2020-05-15T00:39:26.7500000Z",
        "time_period_end": "2020-05-15T00:40:00.0000000Z",
        "time_period_start": "2020-05-15T00:39:00.0000000Z",
        "trades_count": 3,
        "volume_traded": 0.07516618
    },
    {
        "price_close": 9778.91,
        "price_high": 9779.92,
        "price_low": 9769.69,
        "price_open": 9769.69,
        "time_close": "2020-05-15T00:40:59.6430000Z",
        "time_open": "2020-05-15T00:40:23.6100000Z",
        "time_period_end": "2020-05-15T00:41:00.0000000Z",
        "time_period_start": "2020-05-15T00:40:00.0000000Z",
        "trades_count": 50,
        "volume_traded": 12.0843728
    },
    {
        "price_close": 9800.02,
        "price_high": 9802.78,
        "price_low": 9784.76,
        "price_open": 9784.76,
        "time_close": "2020-05-15T00:41:52.1990000Z",
        "time_open": "2020-05-15T00:41:01.5440000Z",
        "time_period_end": "2020-05-15T00:42:00.0000000Z",
        "time_period_start": "2020-05-15T00:41:00.0000000Z",
        "trades_count": 70,
        "volume_traded": 18.74500259
    },
    {
        "price_close": 9808.49,
        "price_high": 9810.0,
        "price_low": 9794.08,
        "price_open": 9794.08,
        "time_close": "2020-05-15T00:42:56.7850000Z",
        "time_open": "2020-05-15T00:42:24.0460000Z",
        "time_period_end": "2020-05-15T00:43:00.0000000Z",
        "time_period_start": "2020-05-15T00:42:00.0000000Z",
        "trades_count": 44,
        "volume_traded": 21.04809545
    },
    {
        "price_close": 9802.47,
        "price_high": 9806.6,
        "price_low": 9795.1,
        "price_open": 9800.98,
        "time_close": "2020-05-15T00:43:45.6550000Z",
        "time_open": "2020-05-15T00:43:02.5570000Z",
        "time_period_end": "2020-05-15T00:44:00.0000000Z",
        "time_period_start": "2020-05-15T00:43:00.0000000Z",
        "trades_count": 30,
        "volume_traded": 0.78117165
    },
    {
        "price_close": 9797.66,
        "price_high": 9803.79,
        "price_low": 9785.79,
        "price_open": 9802.75,
        "time_close": "2020-05-15T00:44:58.6310000Z",
        "time_open": "2020-05-15T00:44:22.1860000Z",
        "time_period_end": "2020-05-15T00:45:00.0000000Z",
        "time_period_start": "2020-05-15T00:44:00.0000000Z",
        "trades_count": 30,
        "volume_traded": 7.40777182
    },
    {
        "price_close": 9790.22,
        "price_high": 9802.6,
        "price_low": 9784.65,
        "price_open": 9793.29,
        "time_close": "2020-05-15T00:45:56.9300000Z",
        "time_open": "2020-05-15T00:45:05.2080000Z",
        "time_period_end": "2020-05-15T00:46:00.0000000Z",
        "time_period_start": "2020-05-15T00:45:00.0000000Z",
        "trades_count": 26,
        "volume_traded": 1.63158242
    },
    {
        "price_close": 9794.7,
        "price_high": 9802.18,
        "price_low": 9790.7,
        "price_open": 9802.18,
        "time_close": "2020-05-15T00:46:28.7820000Z",
        "time_open": "2020-05-15T00:46:04.3090000Z",
        "time_period_end": "2020-05-15T00:47:00.0000000Z",
        "time_period_start": "2020-05-15T00:46:00.0000000Z",
        "trades_count": 15,
        "volume_traded": 0.16233983
    },
    {
        "price_close": 9786.52,
        "price_high": 9795.17,
        "price_low": 9786.44,
        "price_open": 9795.17,
        "time_close": "2020-05-15T00:47:41.9960000Z",
        "time_open": "2020-05-15T00:47:24.8790000Z",
        "time_period_end": "2020-05-15T00:48:00.0000000Z",
        "time_period_start": "2020-05-15T00:47:00.0000000Z",
        "trades_count": 4,
        "volume_traded": 0.12843582
    },
    {
        "price_close": 9791.07,
        "price_high": 9798.66,
        "price_low": 9791.07,
        "price_open": 9791.07,
        "time_close": "2020-05-15T00:48:57.4410000Z",
        "time_open": "2020-05-15T00:48:09.2410000Z",
        "time_period_end": "2020-05-15T00:49:00.0000000Z",
        "time_period_start": "2020-05-15T00:48:00.0000000Z",
        "trades_count": 5,
        "volume_traded": 0.04718777
    },
    {
        "price_close": 9784.32,
        "price_high": 9791.07,
        "price_low": 9782.96,
        "price_open": 9791.07,
        "time_close": "2020-05-15T00:49:36.0880000Z",
        "time_open": "2020-05-15T00:49:10.9100000Z",
        "time_period_end": "2020-05-15T00:50:00.0000000Z",
        "time_period_start": "2020-05-15T00:49:00.0000000Z",
        "trades_count": 5,
        "volume_traded": 1.71527294
    },
    {
        "price_close": 9781.5,
        "price_high": 9788.72,
        "price_low": 9772.47,
        "price_open": 9781.19,
        "time_close": "2020-05-15T00:50:57.6730000Z",
        "time_open": "2020-05-15T00:50:00.2130000Z",
        "time_period_end": "2020-05-15T00:51:00.0000000Z",
        "time_period_start": "2020-05-15T00:50:00.0000000Z",
        "trades_count": 5,
        "volume_traded": 0.1631353
    },
    {
        "price_close": 9782.84,
        "price_high": 9782.84,
        "price_low": 9772.96,
        "price_open": 9772.96,
        "time_close": "2020-05-15T00:51:47.6150000Z",
        "time_open": "2020-05-15T00:51:00.9230000Z",
        "time_period_end": "2020-05-15T00:52:00.0000000Z",
        "time_period_start": "2020-05-15T00:51:00.0000000Z",
        "trades_count": 10,
        "volume_traded": 2.46974812
    },
    {
        "price_close": 9785.16,
        "price_high": 9788.56,
        "price_low": 9782.84,
        "price_open": 9782.84,
        "time_close": "2020-05-15T00:52:42.9850000Z",
        "time_open": "2020-05-15T00:52:02.1480000Z",
        "time_period_end": "2020-05-15T00:53:00.0000000Z",
        "time_period_start": "2020-05-15T00:52:00.0000000Z",
        "trades_count": 5,
        "volume_traded": 0.65702194
    },
    {
        "price_close": 9779.93,
        "price_high": 9793.87,
        "price_low": 9779.93,
        "price_open": 9789.65,
        "time_close": "2020-05-15T00:53:46.2840000Z",
        "time_open": "2020-05-15T00:53:01.0050000Z",
        "time_period_end": "2020-05-15T00:54:00.0000000Z",
        "time_period_start": "2020-05-15T00:53:00.0000000Z",
        "trades_count": 6,
        "volume_traded": 0.66908713
    },
    {
        "price_close": 9774.06,
        "price_high": 9781.32,
        "price_low": 9774.06,
        "price_open": 9779.92,
        "time_close": "2020-05-15T00:54:57.1310000Z",
        "time_open": "2020-05-15T00:54:19.3430000Z",
        "time_period_end": "2020-05-15T00:55:00.0000000Z",
        "time_period_start": "2020-05-15T00:54:00.0000000Z",
        "trades_count": 5,
        "volume_traded": 1.10322665
    },
    {
        "price_close": 9777.14,
        "price_high": 9787.57,
        "price_low": 9774.06,
        "price_open": 9774.06,
        "time_close": "2020-05-15T00:55:38.0010000Z",
        "time_open": "2020-05-15T00:55:00.3490000Z",
        "time_period_end": "2020-05-15T00:56:00.0000000Z",
        "time_period_start": "2020-05-15T00:55:00.0000000Z",
        "trades_count": 10,
        "volume_traded": 0.95888085
    },
    {
        "price_close": 9764.36,
        "price_high": 9774.06,
        "price_low": 9764.36,
        "price_open": 9774.06,
        "time_close": "2020-05-15T00:56:57.7690000Z",
        "time_open": "2020-05-15T00:56:26.9370000Z",
        "time_period_end": "2020-05-15T00:57:00.0000000Z",
        "time_period_start": "2020-05-15T00:56:00.0000000Z",
        "trades_count": 5,
        "volume_traded": 1.20003795
    },
    {
        "price_close": 9765.28,
        "price_high": 9765.28,
        "price_low": 9765.28,
        "price_open": 9765.28,
        "time_close": "2020-05-15T00:57:47.2150000Z",
        "time_open": "2020-05-15T00:57:47.2150000Z",
        "time_period_end": "2020-05-15T00:58:00.0000000Z",
        "time_period_start": "2020-05-15T00:57:00.0000000Z",
        "trades_count": 1,
        "volume_traded": 0.12467605
    },
    {
        "price_close": 9762.34,
        "price_high": 9772.73,
        "price_low": 9762.34,
        "price_open": 9765.54,
        "time_close": "2020-05-15T00:58:54.6140000Z",
        "time_open": "2020-05-15T00:58:11.2830000Z",
        "time_period_end": "2020-05-15T00:59:00.0000000Z",
        "time_period_start": "2020-05-15T00:58:00.0000000Z",
        "trades_count": 12,
        "volume_traded": 1.40598709
    },
    {
        "price_close": 9767.57,
        "price_high": 9772.81,
        "price_low": 9756.21,
        "price_open": 9760.28,
        "time_close": "2020-05-15T00:59:50.7100000Z",
        "time_open": "2020-05-15T00:59:00.3250000Z",
        "time_period_end": "2020-05-15T01:00:00.0000000Z",
        "time_period_start": "2020-05-15T00:59:00.0000000Z",
        "trades_count": 18,
        "volume_traded": 5.96227279
    },
    {
        "price_close": 9751.0,
        "price_high": 9776.03,
        "price_low": 9751.0,
        "price_open": 9776.03,
        "time_close": "2020-05-15T01:00:57.8730000Z",
        "time_open": "2020-05-15T01:00:00.9160000Z",
        "time_period_end": "2020-05-15T01:01:00.0000000Z",
        "time_period_start": "2020-05-15T01:00:00.0000000Z",
        "trades_count": 10,
        "volume_traded": 3.2290169
    },
    {
        "price_close": 9751.42,
        "price_high": 9757.21,
        "price_low": 9750.18,
        "price_open": 9751.01,
        "time_close": "2020-05-15T01:01:53.0290000Z",
        "time_open": "2020-05-15T01:01:08.5020000Z",
        "time_period_end": "2020-05-15T01:02:00.0000000Z",
        "time_period_start": "2020-05-15T01:01:00.0000000Z",
        "trades_count": 14,
        "volume_traded": 5.57233336
    },
    {
        "price_close": 9756.43,
        "price_high": 9758.75,
        "price_low": 9751.42,
        "price_open": 9758.75,
        "time_close": "2020-05-15T01:02:53.6910000Z",
        "time_open": "2020-05-15T01:02:02.9040000Z",
        "time_period_end": "2020-05-15T01:03:00.0000000Z",
        "time_period_start": "2020-05-15T01:02:00.0000000Z",
        "trades_count": 6,
        "volume_traded": 0.11044772
    },
    {
        "price_close": 9749.35,
        "price_high": 9758.93,
        "price_low": 9749.35,
        "price_open": 9758.93,
        "time_close": "2020-05-15T01:03:42.4890000Z",
        "time_open": "2020-05-15T01:03:24.3270000Z",
        "time_period_end": "2020-05-15T01:04:00.0000000Z",
        "time_period_start": "2020-05-15T01:03:00.0000000Z",
        "trades_count": 2,
        "volume_traded": 0.02079179
    },
    {
        "price_close": 9738.94,
        "price_high": 9750.25,
        "price_low": 9738.94,
        "price_open": 9750.25,
        "time_close": "2020-05-15T01:04:58.0390000Z",
        "time_open": "2020-05-15T01:04:32.6190000Z",
        "time_period_end": "2020-05-15T01:05:00.0000000Z",
        "time_period_start": "2020-05-15T01:04:00.0000000Z",
        "trades_count": 5,
        "volume_traded": 3.61295304
    },
    {
        "price_close": 9755.75,
        "price_high": 9755.75,
        "price_low": 9748.44,
        "price_open": 9748.44,
        "time_close": "2020-05-15T01:05:54.9250000Z",
        "time_open": "2020-05-15T01:05:27.2830000Z",
        "time_period_end": "2020-05-15T01:06:00.0000000Z",
        "time_period_start": "2020-05-15T01:05:00.0000000Z",
        "trades_count": 5,
        "volume_traded": 0.63325506
    },
    {
        "price_close": 9755.47,
        "price_high": 9760.99,
        "price_low": 9752.97,
        "price_open": 9752.97,
        "time_close": "2020-05-15T01:06:58.7810000Z",
        "time_open": "2020-05-15T01:06:01.8660000Z",
        "time_period_end": "2020-05-15T01:07:00.0000000Z",
        "time_period_start": "2020-05-15T01:06:00.0000000Z",
        "trades_count": 5,
        "volume_traded": 0.09013678
    },
    {
        "price_close": 9754.66,
        "price_high": 9762.02,
        "price_low": 9750.63,
        "price_open": 9761.52,
        "time_close": "2020-05-15T01:07:58.0350000Z",
        "time_open": "2020-05-15T01:07:28.6780000Z",
        "time_period_end": "2020-05-15T01:08:00.0000000Z",
        "time_period_start": "2020-05-15T01:07:00.0000000Z",
        "trades_count": 37,
        "volume_traded": 13.79553415
    },
    {
        "price_close": 9744.25,
        "price_high": 9752.73,
        "price_low": 9744.25,
        "price_open": 9752.63,
        "time_close": "2020-05-15T01:08:59.0630000Z",
        "time_open": "2020-05-15T01:08:56.4500000Z",
        "time_period_end": "2020-05-15T01:09:00.0000000Z",
        "time_period_start": "2020-05-15T01:08:00.0000000Z",
        "trades_count": 4,
        "volume_traded": 0.04334398
    },
    {
        "price_close": 9753.91,
        "price_high": 9759.1,
        "price_low": 9745.9,
        "price_open": 9745.9,
        "time_close": "2020-05-15T01:09:46.6580000Z",
        "time_open": "2020-05-15T01:09:08.3150000Z",
        "time_period_end": "2020-05-15T01:10:00.0000000Z",
        "time_period_start": "2020-05-15T01:09:00.0000000Z",
        "trades_count": 20,
        "volume_traded": 1.397061
    },
    {
        "price_close": 9758.59,
        "price_high": 9758.59,
        "price_low": 9753.76,
        "price_open": 9753.76,
        "time_close": "2020-05-15T01:10:55.9510000Z",
        "time_open": "2020-05-15T01:10:00.9630000Z",
        "time_period_end": "2020-05-15T01:11:00.0000000Z",
        "time_period_start": "2020-05-15T01:10:00.0000000Z",
        "trades_count": 5,
        "volume_traded": 1.85741511
    },
    {
        "price_close": 9740.0,
        "price_high": 9753.57,
        "price_low": 9740.0,
        "price_open": 9749.76,
        "time_close": "2020-05-15T01:11:57.5630000Z",
        "time_open": "2020-05-15T01:11:13.7790000Z",
        "time_period_end": "2020-05-15T01:12:00.0000000Z",
        "time_period_start": "2020-05-15T01:11:00.0000000Z",
        "trades_count": 13,
        "volume_traded": 1.01776605
    },
    {
        "price_close": 9738.71,
        "price_high": 9744.81,
        "price_low": 9738.71,
        "price_open": 9740.0,
        "time_close": "2020-05-15T01:12:59.3470000Z",
        "time_open": "2020-05-15T01:12:00.1860000Z",
        "time_period_end": "2020-05-15T01:13:00.0000000Z",
        "time_period_start": "2020-05-15T01:12:00.0000000Z",
        "trades_count": 12,
        "volume_traded": 4.52124847
    },
    {
        "price_close": 9733.26,
        "price_high": 9746.77,
        "price_low": 9733.26,
        "price_open": 9742.88,
        "time_close": "2020-05-15T01:13:59.8280000Z",
        "time_open": "2020-05-15T01:13:22.0640000Z",
        "time_period_end": "2020-05-15T01:14:00.0000000Z",
        "time_period_start": "2020-05-15T01:13:00.0000000Z",
        "trades_count": 16,
        "volume_traded": 3.56378046
    },
    {
        "price_close": 9741.86,
        "price_high": 9749.56,
        "price_low": 9741.35,
        "price_open": 9742.91,
        "time_close": "2020-05-15T01:14:59.6440000Z",
        "time_open": "2020-05-15T01:14:13.9620000Z",
        "time_period_end": "2020-05-15T01:15:00.0000000Z",
        "time_period_start": "2020-05-15T01:14:00.0000000Z",
        "trades_count": 18,
        "volume_traded": 3.31669169
    },
    {
        "price_close": 9744.96,
        "price_high": 9745.09,
        "price_low": 9740.18,
        "price_open": 9745.09,
        "time_close": "2020-05-15T01:15:47.9490000Z",
        "time_open": "2020-05-15T01:15:01.4560000Z",
        "time_period_end": "2020-05-15T01:16:00.0000000Z",
        "time_period_start": "2020-05-15T01:15:00.0000000Z",
        "trades_count": 15,
        "volume_traded": 0.6112429
    },
    {
        "price_close": 9736.14,
        "price_high": 9745.51,
        "price_low": 9734.26,
        "price_open": 9738.39,
        "time_close": "2020-05-15T01:16:59.9230000Z",
        "time_open": "2020-05-15T01:16:25.7590000Z",
        "time_period_end": "2020-05-15T01:17:00.0000000Z",
        "time_period_start": "2020-05-15T01:16:00.0000000Z",
        "trades_count": 13,
        "volume_traded": 0.5727391
    },
    {
        "price_close": 9752.0,
        "price_high": 9752.0,
        "price_low": 9735.81,
        "price_open": 9743.39,
        "time_close": "2020-05-15T01:17:57.3940000Z",
        "time_open": "2020-05-15T01:17:14.6720000Z",
        "time_period_end": "2020-05-15T01:18:00.0000000Z",
        "time_period_start": "2020-05-15T01:17:00.0000000Z",
        "trades_count": 32,
        "volume_traded": 10.86361089
    },
    {
        "price_close": 9761.12,
        "price_high": 9761.59,
        "price_low": 9754.58,
        "price_open": 9754.58,
        "time_close": "2020-05-15T01:18:54.4620000Z",
        "time_open": "2020-05-15T01:18:02.0650000Z",
        "time_period_end": "2020-05-15T01:19:00.0000000Z",
        "time_period_start": "2020-05-15T01:18:00.0000000Z",
        "trades_count": 9,
        "volume_traded": 2.03304264
    },
    {
        "price_close": 9761.25,
        "price_high": 9761.37,
        "price_low": 9752.77,
        "price_open": 9752.77,
        "time_close": "2020-05-15T01:19:48.7970000Z",
        "time_open": "2020-05-15T01:19:02.2240000Z",
        "time_period_end": "2020-05-15T01:20:00.0000000Z",
        "time_period_start": "2020-05-15T01:19:00.0000000Z",
        "trades_count": 4,
        "volume_traded": 0.10460622
    },
    {
        "price_close": 9751.72,
        "price_high": 9760.55,
        "price_low": 9751.24,
        "price_open": 9755.75,
        "time_close": "2020-05-15T01:20:49.2350000Z",
        "time_open": "2020-05-15T01:20:20.7810000Z",
        "time_period_end": "2020-05-15T01:21:00.0000000Z",
        "time_period_start": "2020-05-15T01:20:00.0000000Z",
        "trades_count": 15,
        "volume_traded": 7.46052902
    },
    {
        "price_close": 9754.36,
        "price_high": 9760.02,
        "price_low": 9752.87,
        "price_open": 9752.87,
        "time_close": "2020-05-15T01:21:38.6520000Z",
        "time_open": "2020-05-15T01:21:00.0370000Z",
        "time_period_end": "2020-05-15T01:22:00.0000000Z",
        "time_period_start": "2020-05-15T01:21:00.0000000Z",
        "trades_count": 7,
        "volume_traded": 0.19154879
    },
    {
        "price_close": 9759.75,
        "price_high": 9759.75,
        "price_low": 9745.7,
        "price_open": 9752.38,
        "time_close": "2020-05-15T01:22:42.0610000Z",
        "time_open": "2020-05-15T01:22:25.5080000Z",
        "time_period_end": "2020-05-15T01:23:00.0000000Z",
        "time_period_start": "2020-05-15T01:22:00.0000000Z",
        "trades_count": 19,
        "volume_traded": 2.21708152
    },
    {
        "price_close": 9772.7,
        "price_high": 9772.7,
        "price_low": 9766.82,
        "price_open": 9767.19,
        "time_close": "2020-05-15T01:23:52.0600000Z",
        "time_open": "2020-05-15T01:23:27.4430000Z",
        "time_period_end": "2020-05-15T01:24:00.0000000Z",
        "time_period_start": "2020-05-15T01:23:00.0000000Z",
        "trades_count": 22,
        "volume_traded": 6.30437442
    },
    {
        "price_close": 9774.1,
        "price_high": 9774.1,
        "price_low": 9763.15,
        "price_open": 9763.15,
        "time_close": "2020-05-15T01:24:59.9150000Z",
        "time_open": "2020-05-15T01:24:25.8150000Z",
        "time_period_end": "2020-05-15T01:25:00.0000000Z",
        "time_period_start": "2020-05-15T01:24:00.0000000Z",
        "trades_count": 29,
        "volume_traded": 11.68316596
    },
    {
        "price_close": 9767.1,
        "price_high": 9771.47,
        "price_low": 9767.1,
        "price_open": 9771.45,
        "time_close": "2020-05-15T01:25:56.9180000Z",
        "time_open": "2020-05-15T01:25:01.9130000Z",
        "time_period_end": "2020-05-15T01:26:00.0000000Z",
        "time_period_start": "2020-05-15T01:25:00.0000000Z",
        "trades_count": 9,
        "volume_traded": 1.96205414
    },
    {
        "price_close": 9767.94,
        "price_high": 9767.94,
        "price_low": 9761.3,
        "price_open": 9763.17,
        "time_close": "2020-05-15T01:26:54.0730000Z",
        "time_open": "2020-05-15T01:26:23.5650000Z",
        "time_period_end": "2020-05-15T01:27:00.0000000Z",
        "time_period_start": "2020-05-15T01:26:00.0000000Z",
        "trades_count": 7,
        "volume_traded": 1.4703954
    },
    {
        "price_close": 9767.84,
        "price_high": 9767.94,
        "price_low": 9762.54,
        "price_open": 9763.72,
        "time_close": "2020-05-15T01:27:45.7250000Z",
        "time_open": "2020-05-15T01:27:01.9780000Z",
        "time_period_end": "2020-05-15T01:28:00.0000000Z",
        "time_period_start": "2020-05-15T01:27:00.0000000Z",
        "trades_count": 8,
        "volume_traded": 2.1974169
    },
    {
        "price_close": 9768.79,
        "price_high": 9768.8,
        "price_low": 9768.79,
        "price_open": 9768.8,
        "time_close": "2020-05-15T01:28:23.4690000Z",
        "time_open": "2020-05-15T01:28:22.8030000Z",
        "time_period_end": "2020-05-15T01:29:00.0000000Z",
        "time_period_start": "2020-05-15T01:28:00.0000000Z",
        "trades_count": 2,
        "volume_traded": 0.01901903
    },
    {
        "price_close": 9759.63,
        "price_high": 9766.8,
        "price_low": 9759.63,
        "price_open": 9766.79,
        "time_close": "2020-05-15T01:29:48.1080000Z",
        "time_open": "2020-05-15T01:29:01.5960000Z",
        "time_period_end": "2020-05-15T01:30:00.0000000Z",
        "time_period_start": "2020-05-15T01:29:00.0000000Z",
        "trades_count": 8,
        "volume_traded": 0.11968736
    },
    {
        "price_close": 9755.77,
        "price_high": 9762.02,
        "price_low": 9755.77,
        "price_open": 9762.02,
        "time_close": "2020-05-15T01:30:47.5880000Z",
        "time_open": "2020-05-15T01:30:21.9470000Z",
        "time_period_end": "2020-05-15T01:31:00.0000000Z",
        "time_period_start": "2020-05-15T01:30:00.0000000Z",
        "trades_count": 5,
        "volume_traded": 0.09080339
    },
    {
        "price_close": 9750.58,
        "price_high": 9755.77,
        "price_low": 9750.58,
        "price_open": 9755.77,
        "time_close": "2020-05-15T01:31:49.9480000Z",
        "time_open": "2020-05-15T01:31:02.5150000Z",
        "time_period_end": "2020-05-15T01:32:00.0000000Z",
        "time_period_start": "2020-05-15T01:31:00.0000000Z",
        "trades_count": 3,
        "volume_traded": 0.01458541
    },
    {
        "price_close": 9752.83,
        "price_high": 9754.87,
        "price_low": 9744.79,
        "price_open": 9751.12,
        "time_close": "2020-05-15T01:32:50.9440000Z",
        "time_open": "2020-05-15T01:32:09.3280000Z",
        "time_period_end": "2020-05-15T01:33:00.0000000Z",
        "time_period_start": "2020-05-15T01:32:00.0000000Z",
        "trades_count": 18,
        "volume_traded": 0.57602412
    },
    {
        "price_close": 9744.79,
        "price_high": 9749.36,
        "price_low": 9744.79,
        "price_open": 9745.54,
        "time_close": "2020-05-15T01:33:59.4430000Z",
        "time_open": "2020-05-15T01:33:02.6020000Z",
        "time_period_end": "2020-05-15T01:34:00.0000000Z",
        "time_period_start": "2020-05-15T01:33:00.0000000Z",
        "trades_count": 16,
        "volume_traded": 7.42484355
    },
    {
        "price_close": 9750.48,
        "price_high": 9750.98,
        "price_low": 9741.22,
        "price_open": 9745.44,
        "time_close": "2020-05-15T01:34:43.9820000Z",
        "time_open": "2020-05-15T01:34:06.0340000Z",
        "time_period_end": "2020-05-15T01:35:00.0000000Z",
        "time_period_start": "2020-05-15T01:34:00.0000000Z",
        "trades_count": 10,
        "volume_traded": 1.79016149
    },
    {
        "price_close": 9735.54,
        "price_high": 9739.13,
        "price_low": 9735.54,
        "price_open": 9739.13,
        "time_close": "2020-05-15T01:35:40.8140000Z",
        "time_open": "2020-05-15T01:35:32.0140000Z",
        "time_period_end": "2020-05-15T01:36:00.0000000Z",
        "time_period_start": "2020-05-15T01:35:00.0000000Z",
        "trades_count": 3,
        "volume_traded": 0.76468196
    },
    {
        "price_close": 9730.46,
        "price_high": 9738.85,
        "price_low": 9730.46,
        "price_open": 9735.22,
        "time_close": "2020-05-15T01:36:54.7820000Z",
        "time_open": "2020-05-15T01:36:06.9490000Z",
        "time_period_end": "2020-05-15T01:37:00.0000000Z",
        "time_period_start": "2020-05-15T01:36:00.0000000Z",
        "trades_count": 7,
        "volume_traded": 0.13296639
    },
    {
        "price_close": 9735.68,
        "price_high": 9742.07,
        "price_low": 9733.38,
        "price_open": 9742.07,
        "time_close": "2020-05-15T01:37:45.2890000Z",
        "time_open": "2020-05-15T01:37:02.3110000Z",
        "time_period_end": "2020-05-15T01:38:00.0000000Z",
        "time_period_start": "2020-05-15T01:37:00.0000000Z",
        "trades_count": 7,
        "volume_traded": 0.14483748
    },
    {
        "price_close": 9743.69,
        "price_high": 9743.69,
        "price_low": 9743.69,
        "price_open": 9743.69,
        "time_close": "2020-05-15T01:38:01.1400000Z",
        "time_open": "2020-05-15T01:38:01.1400000Z",
        "time_period_end": "2020-05-15T01:39:00.0000000Z",
        "time_period_start": "2020-05-15T01:38:00.0000000Z",
        "trades_count": 1,
        "volume_traded": 0.04491291
    },
    {
        "price_close": 9763.6,
        "price_high": 9763.6,
        "price_low": 9750.92,
        "price_open": 9750.92,
        "time_close": "2020-05-15T01:39:38.3410000Z",
        "time_open": "2020-05-15T01:39:07.0520000Z",
        "time_period_end": "2020-05-15T01:40:00.0000000Z",
        "time_period_start": "2020-05-15T01:39:00.0000000Z",
        "trades_count": 13,
        "volume_traded": 5.21123498
    }
]